desktop.ini
skdim/__init__.py
skdim/_commonfuncs.py
skdim/_version.py
skdim/datasets.py
skdim/desktop.ini
skdim/id/_CorrInt.py
skdim/id/_DANCo.py
skdim/id/_DANCoUtils.py
skdim/id/_ESS.py
skdim/id/_FisherS.py
skdim/id/_KNN.py
skdim/id/_MADA.py
skdim/id/_MLE.py
skdim/id/_MOM.py
skdim/id/_MiND_ML.py
skdim/id/_PCA.py
skdim/id/_TLE.py
skdim/id/_TwoNN.py
skdim/id/__init__.py
skdim/id/desktop.ini
skdim/tests/__init__.py
skdim/tests/desktop.ini
skdim/tests/test_all_params.py
skdim/tests/test_results.py
scikit_dimension-0.3.4.dist-info/LICENSE
scikit_dimension-0.3.4.dist-info/METADATA
scikit_dimension-0.3.4.dist-info/WHEEL
scikit_dimension-0.3.4.dist-info/top_level.txt
scikit_dimension-0.3.4.dist-info/RECORD
